van.py
van-0.0.6.dist-info/DESCRIPTION.rst
van-0.0.6.dist-info/METADATA
van-0.0.6.dist-info/RECORD
van-0.0.6.dist-info/WHEEL
van-0.0.6.dist-info/metadata.json
van-0.0.6.dist-info/top_level.txt
