Metadata-Version: 2.0
Name: van
Version: 0.0.6
Summary: Fanfou SDK in Python
Home-page: https://github.com/j178/van
Author: John Jiang
Author-email: nigelchiang@outlook.com
License: MIT
Keywords: fanfou,sdk
Platform: UNKNOWN
Requires-Dist: requests-oauthlib (==0.8.0)
